clicksend_client/__init__.py
clicksend_client/api_client.py
clicksend_client/configuration.py
clicksend_client/rest.py
clicksend_client/api/__init__.py
clicksend_client/api/account_api.py
clicksend_client/api/account_recharge_api.py
clicksend_client/api/contact_api.py
clicksend_client/api/contact_list_api.py
clicksend_client/api/countries_api.py
clicksend_client/api/delivery_issues_api.py
clicksend_client/api/detect_address_api.py
clicksend_client/api/email_delivery_receipt_rules_api.py
clicksend_client/api/email_marketing_api.py
clicksend_client/api/email_to_sms_api.py
clicksend_client/api/fax_api.py
clicksend_client/api/fax_delivery_receipt_rules_api.py
clicksend_client/api/global_sending_api.py
clicksend_client/api/inbound_fax_rules_api.py
clicksend_client/api/inbound_sms_rules_api.py
clicksend_client/api/master_email_templates_api.py
clicksend_client/api/mms_api.py
clicksend_client/api/mms_campaign_api.py
clicksend_client/api/number_api.py
clicksend_client/api/post_letter_api.py
clicksend_client/api/post_postcard_api.py
clicksend_client/api/post_return_address_api.py
clicksend_client/api/referral_account_api.py
clicksend_client/api/reseller_account_api.py
clicksend_client/api/search_api.py
clicksend_client/api/sms_api.py
clicksend_client/api/sms_campaign_api.py
clicksend_client/api/sms_delivery_receipt_rules_api.py
clicksend_client/api/statistics_api.py
clicksend_client/api/subaccount_api.py
clicksend_client/api/timezones_api.py
clicksend_client/api/transactional_email_api.py
clicksend_client/api/transfer_credit_api.py
clicksend_client/api/upload_api.py
clicksend_client/api/user_email_templates_api.py
clicksend_client/api/voice_api.py
clicksend_client/api/voice_delivery_receipt_rules_api.py
clicksend_client/models/__init__.py
clicksend_client/models/account.py
clicksend_client/models/account_forgot_password_verify.py
clicksend_client/models/account_verify.py
clicksend_client/models/address.py
clicksend_client/models/attachment.py
clicksend_client-5.0.78.dist-info/METADATA
clicksend_client-5.0.78.dist-info/WHEEL
clicksend_client-5.0.78.dist-info/top_level.txt
clicksend_client-5.0.78.dist-info/RECORD
