Metadata-Version: 2.1
Name: clicksend-client
Version: 5.0.78
Summary: ClickSend v3 API
Home-page: 
Author-email: support@clicksend.com
Keywords: Swagger,ClickSend v3 API
Requires-Dist: certifi >=2017.4.17
Requires-Dist: python-dateutil >=2.1
Requires-Dist: six >=1.10
Requires-Dist: urllib3 >=1.23
